open_autonomy_compose/__init__.py
open_autonomy_compose/cli/__init__.py
open_autonomy_compose/cli/check.py
open_autonomy_compose/cli/context.py
open_autonomy_compose/cli/fsm.py
open_autonomy_compose/cli/inspect.py
open_autonomy_compose/cli/new.py
open_autonomy_compose/cli/scaffold.py
open_autonomy_compose/constants.py
open_autonomy_compose/data/__init__.py
open_autonomy_compose/data/site/404.html
open_autonomy_compose/data/site/_next/static/chunks/213-631b62a75f4811c5.js
open_autonomy_compose/data/site/_next/static/chunks/596-821b8f72a9b5817b.js
open_autonomy_compose/data/site/_next/static/chunks/app/layout-936e8a344d197d34.js
open_autonomy_compose/data/site/_next/static/chunks/app/page-aed009dcc15caf61.js
open_autonomy_compose/data/site/_next/static/chunks/c37d3baf-3f70362cc6f4fce3.js
open_autonomy_compose/data/site/_next/static/chunks/fd9d1056-2aa8cf7a7ffac65e.js
open_autonomy_compose/data/site/_next/static/chunks/framework-8883d1e9be70c3da.js
open_autonomy_compose/data/site/_next/static/chunks/main-119c42ec3028f919.js
open_autonomy_compose/data/site/_next/static/chunks/main-app-6644b32c2e6c4090.js
open_autonomy_compose/data/site/_next/static/chunks/pages/_app-52924524f99094ab.js
open_autonomy_compose/data/site/_next/static/chunks/pages/_error-c92d5c4bb2b49926.js
open_autonomy_compose/data/site/_next/static/chunks/polyfills-78c92fac7aa8fdd8.js
open_autonomy_compose/data/site/_next/static/chunks/webpack-d9ed3592a9e87f33.js
open_autonomy_compose/data/site/_next/static/css/7a11c3935a1caf00.css
open_autonomy_compose/data/site/_next/static/css/b4846eed11c4725f.css
open_autonomy_compose/data/site/_next/static/iM88MF7NutYb6Pip8Ysc3/_buildManifest.js
open_autonomy_compose/data/site/_next/static/iM88MF7NutYb6Pip8Ysc3/_ssgManifest.js
open_autonomy_compose/data/site/_next/static/media/26a46d62cd723877-s.woff2
open_autonomy_compose/data/site/_next/static/media/55c55f0601d81cf3-s.woff2
open_autonomy_compose/data/site/_next/static/media/581909926a08bbc8-s.woff2
open_autonomy_compose-0.1.1.dist-info/LICENSE
open_autonomy_compose-0.1.1.dist-info/METADATA
open_autonomy_compose-0.1.1.dist-info/WHEEL
open_autonomy_compose-0.1.1.dist-info/entry_points.txt
open_autonomy_compose-0.1.1.dist-info/RECORD
