Metadata-Version: 2.1
Name: open-autonomy-compose
Version: 0.1.1
Summary: FSM Composer for open-autonomy framework
License: Apache-2.0
Author: angrybayblade
Author-email: vptl185@gmail.com
Requires-Python: >=3.8,<4
Classifier: License :: OSI Approved :: Apache Software License
Classifier: Programming Language :: Python :: 3
Classifier: Programming Language :: Python :: 3.8
Classifier: Programming Language :: Python :: 3.9
Classifier: Programming Language :: Python :: 3.10
Classifier: Programming Language :: Python :: 3.11
Classifier: Programming Language :: Python :: 3.12
Requires-Dist: black (==23.1.0)
Requires-Dist: clea (==0.1.0rc4)
Requires-Dist: flask (==2.1.3)
Requires-Dist: open-aea-cli-ipfs (==1.55.0)
Requires-Dist: open-autonomy[all] (==0.15.2)
Requires-Dist: pyyaml (==6.0.1)
Requires-Dist: starlette (==0.37.2)
Requires-Dist: toml (==0.10.2)
Requires-Dist: tomte[black,isort] (==0.2.17)
Requires-Dist: uvicorn (==0.30.5)
